discordbio/__init__.py
discordbio/client.py
discordbio/errors.py
discordbio/models/__init__.py
discordbio/models/connections.py
discordbio/models/user_details.py
discordbio-1.2.0.data/data/ReleaseNotes.md
discordbio-1.2.0.dist-info/LICENSE
discordbio-1.2.0.dist-info/METADATA
discordbio-1.2.0.dist-info/WHEEL
discordbio-1.2.0.dist-info/top_level.txt
discordbio-1.2.0.dist-info/RECORD
