Metadata-Version: 2.1
Name: discordbio
Version: 1.2.0
Summary: An asynchronous wrapper for the discord.bio api
Home-page: https://github.com/GamingGeek/discordbio
Author: GamingGeek (Jake Ward)
Author-email: geek@gaminggeek.dev
License: UNKNOWN
Platform: UNKNOWN
Requires-Dist: aiohttp (>=3.6.2)
Requires-Dist: python-dateutil (>=2.8.0)
